behaveml/__init__.py
behaveml/config.py
behaveml/features.py
behaveml/generic_features.py
behaveml/interpolation.py
behaveml/io.py
behaveml/mars_features.py
behaveml/ml.py
behaveml/models.py
behaveml/plot.py
behaveml/unsupervised.py
behaveml/utils.py
behaveml/version.py
behaveml/video.py
behaveml/dl/__init__.py
behaveml/dl/dl_features.py
behaveml/dl/dl_generators.py
behaveml/dl/dl_models.py
behaveml/dl/feature_engineering.py
behaveml/dl/grid_searches.py
behaveml-0.2.9.dist-info/LICENSE
behaveml-0.2.9.dist-info/METADATA
behaveml-0.2.9.dist-info/WHEEL
behaveml-0.2.9.dist-info/top_level.txt
behaveml-0.2.9.dist-info/RECORD
