Metadata-Version: 2.1
Name: behaveml
Version: 0.2.9
Summary: Machine learning for animal behavior analysis
Home-page: https://github.com/benlansdell/behaveml
Author: Ben Lansdell
Author-email: ben.lansdell@gmail.com
Project-URL: Bug Tracker, https://github.com/benlansdell/behaveml/issues
Classifier: Programming Language :: Python :: 3
Classifier: License :: OSI Approved :: MIT License
Classifier: Operating System :: OS Independent
Requires-Python: >=3.6
License-File: LICENSE
Requires-Dist: numpy
Requires-Dist: pandas
Requires-Dist: scikit-learn
Requires-Dist: tqdm
Requires-Dist: typeguard
Requires-Dist: typing
Requires-Dist: matplotlib
Requires-Dist: scikit-image
Requires-Dist: umap-learn
Provides-Extra: all
Requires-Dist: tensorflow (==2.4.1) ; extra == 'all'
Requires-Dist: keras (==2.4.3) ; extra == 'all'
